milvus_beir-1.0.0.dist-info/METADATA
milvus_beir-1.0.0.dist-info/WHEEL
milvus_beir-1.0.0.dist-info/entry_points.txt
milvus_beir-1.0.0.dist-info/licenses/LICENSE
milvus_beir/__init__.py
milvus_beir/cli/__init__.py
milvus_beir/cli/search_cli.py
milvus_beir/retrieval/__init__.py
milvus_beir/retrieval/search/__init__.py
milvus_beir/retrieval/search/dense/__init__.py
milvus_beir/retrieval/search/dense/dense_search.py
milvus_beir/retrieval/search/hybrid/__init__.py
milvus_beir/retrieval/search/hybrid/bm25_hybrid_search.py
milvus_beir/retrieval/search/hybrid/sparse_hybrid_search.py
milvus_beir/retrieval/search/lexical/__init__.py
milvus_beir/retrieval/search/lexical/bm25_search.py
milvus_beir/retrieval/search/lexical/multi_match_search.py
milvus_beir/retrieval/search/milvus.py
milvus_beir/retrieval/search/sparse/__init__.py
milvus_beir/retrieval/search/sparse/sparse_search.py
milvus_beir/utils.py
milvus_beir-1.0.0.dist-info/RECORD
