Metadata-Version: 2.1
Name: milvus_beir
Version: 1.0.0
Summary: A Python library that integrates Milvus vector database with BEIR (Benchmarking IR) for efficient information retrieval and evaluation.
Author-Email: zhuwenxing <wenxing.zhu@zilliz.com>
License: MIT
Requires-Python: >=3.10
Requires-Dist: pymilvus>=2.5.0
Requires-Dist: numpy<2.0.0
Requires-Dist: torch<=2.2.2
Requires-Dist: milvus-model>=0.2.10
Requires-Dist: beir>=2.0.0
Requires-Dist: click>=8.0.0
Requires-Dist: ranx>=0.3.20
Requires-Dist: ir-datasets>=0.5.9
